pyConics/__init__.py
pyConics/agobj.py
pyConics/conics/__init__.py
pyConics/conics/conic.py
pyConics/conics/utils.py
pyConics/constants.py
pyConics/errors.py
pyConics/line.py
pyConics/origin.py
pyConics/plotting/__init__.py
pyConics/plotting/axes.py
pyConics/plotting/figure.py
pyConics/plotting/utils.py
pyConics/point.py
pyConics/tolerance.py
pyConics/utils.py
pyconics-1.1.0.dist-info/LICENSE
pyconics-1.1.0.dist-info/METADATA
pyconics-1.1.0.dist-info/WHEEL
pyconics-1.1.0.dist-info/RECORD
