Metadata-Version: 2.1
Name: pyConics
Version: 1.1.0
Summary: Handle points, lines and conics by using algebraic geometry.
License: GNU General Public License v3.0
Author: Jefferson Osowsky
Requires-Python: >=3.10,<4.0
Classifier: License :: Other/Proprietary License
Classifier: Programming Language :: Python :: 3
Classifier: Programming Language :: Python :: 3.10
Classifier: Programming Language :: Python :: 3.11
Requires-Dist: matplotlib (>=3.8.0,<4.0.0)
Requires-Dist: pyautogui (>=0.9.54,<0.10.0)
